hehe_noob_cli-1.1.0.dist-info/licenses/LICENSE
noob_cli/__init__.py
noob_cli/cli.py
hehe_noob_cli-1.1.0.dist-info/METADATA
hehe_noob_cli-1.1.0.dist-info/WHEEL
hehe_noob_cli-1.1.0.dist-info/entry_points.txt
hehe_noob_cli-1.1.0.dist-info/top_level.txt
hehe_noob_cli-1.1.0.dist-info/RECORD
