Metadata-Version: 2.4
Name: hehe-noob-cli
Version: 1.1.0
Summary: AI-powered command-line code generator using Google Gemini - HeHe Noob Edition
Author-email: Tur Za <write2turza@gmail.com>
License-Expression: MIT
Project-URL: Homepage, https://github.com/turzapodder/hehe-noob-cli
Project-URL: Bug Tracker, https://github.com/yourusername/hehe-noob-cli/issues
Project-URL: Repository, https://github.com/turzapodder/hehe-noob-cli
Keywords: ai,code-generation,gemini,cli,development,hehe-noob
Classifier: Development Status :: 4 - Beta
Classifier: Intended Audience :: Developers
Classifier: Operating System :: OS Independent
Classifier: Programming Language :: Python :: 3
Classifier: Programming Language :: Python :: 3.8
Classifier: Programming Language :: Python :: 3.9
Classifier: Programming Language :: Python :: 3.10
Classifier: Programming Language :: Python :: 3.11
Classifier: Programming Language :: Python :: 3.12
Classifier: Topic :: Software Development :: Code Generators
Classifier: Topic :: Software Development :: Libraries :: Python Modules
Requires-Python: >=3.8
License-File: LICENSE
Requires-Dist: google-generativeai>=0.8.0
Requires-Dist: rich>=13.0.0
Requires-Dist: pathlib2>=2.3.0
Requires-Dist: keyring>=23.0.0
Requires-Dist: cryptography>=3.0.0
Provides-Extra: dev
Requires-Dist: pytest>=7.0; extra == "dev"
Requires-Dist: black>=22.0; extra == "dev"
Requires-Dist: flake8>=5.0; extra == "dev"
Requires-Dist: mypy>=0.991; extra == "dev"
Dynamic: license-file
